Metadata-Version: 1.1
Name: commodity-tool
Version: 0.5.dev0
Summary: UNKNOWN
Home-page: https://github.com/johnnymac0515/Commodity-Project
Author: John Macnamara
Author-email: john.macnamara.dev@gmail.com
License: MIT License
